BCGM_PY_CMD/__init__.py
BCGM_PY_CMD/__main__.py
BCGM_PY_CMD/feature_handler.py
BCGM_PY_CMD/helper.py
BCGM_PY_CMD/encrypt_decrypt/__init__.py
BCGM_PY_CMD/encrypt_decrypt/decrypt_pack.py
BCGM_PY_CMD/encrypt_decrypt/encrypt_pack.py
BCGM_PY_CMD/file_mods/__init__.py
BCGM_PY_CMD/file_mods/enemy_mod.py
BCGM_PY_CMD/file_mods/stage_mod.py
BCGM_PY_CMD/file_mods/unit_mod.py
BCGM_PY_CMD/files/__init__.py
BCGM_PY_CMD/files/version.txt
BCGM_PY_CMD/libnative/__init__.py
BCGM_PY_CMD/libnative/find_order.py
BCGM_PY_CMD/libnative/write_libnative_md5.py
battle_cats_game_modder_cmd_line_version-1.0.8.data/data/files/version.txt
battle_cats_game_modder_cmd_line_version-1.0.8.dist-info/LICENSE
battle_cats_game_modder_cmd_line_version-1.0.8.dist-info/METADATA
battle_cats_game_modder_cmd_line_version-1.0.8.dist-info/WHEEL
battle_cats_game_modder_cmd_line_version-1.0.8.dist-info/top_level.txt
battle_cats_game_modder_cmd_line_version-1.0.8.dist-info/RECORD
