Metadata-Version: 2.1
Name: battle-cats-game-modder-cmd-line-version
Version: 1.0.8
Summary: A battle cats tool for modifying, encrypting, and decrypting game files
Home-page: https://github.com/j0912345/BCGM-Python-cmd-line-version
Author: jo912345
Classifier: Programming Language :: Python :: 3
Classifier: License :: OSI Approved :: MIT License
Classifier: Operating System :: OS Independent
Requires-Python: >=3.6
License-File: LICENSE
Requires-Dist: colored
Requires-Dist: tk
Requires-Dist: alive-progress
Requires-Dist: pycryptodomex
Requires-Dist: requests
